LICENSE
README.md
setup.py
csrfmap/__init__.py
csrfmap/__main__.py
csrfmap/__meta__.py
csrfmap/csrfmap.py
csrfmap/payloads.py
csrfmap.egg-info/PKG-INFO
csrfmap.egg-info/SOURCES.txt
csrfmap.egg-info/dependency_links.txt
csrfmap.egg-info/entry_points.txt
csrfmap.egg-info/not-zip-safe
csrfmap.egg-info/top_level.txt
test/__init__.py